hyblock_capital_sdk/__init__.py
hyblock_capital_sdk/api/__init__.py
hyblock_capital_sdk/api/api_usage_api.py
hyblock_capital_sdk/api/catalog_api.py
hyblock_capital_sdk/api/funding_rate_api.py
hyblock_capital_sdk/api/liquidity_api.py
hyblock_capital_sdk/api/longs_and_shorts_api.py
hyblock_capital_sdk/api/open_interest_api.py
hyblock_capital_sdk/api/options_api.py
hyblock_capital_sdk/api/orderbook_api.py
hyblock_capital_sdk/api/orderflow_api.py
hyblock_capital_sdk/api/profile_tool_api.py
hyblock_capital_sdk/api/sentiment_api.py
hyblock_capital_sdk/api_client.py
hyblock_capital_sdk/api_response.py
hyblock_capital_sdk/auth.py
hyblock_capital_sdk/client.py
hyblock_capital_sdk/configuration.py
hyblock_capital_sdk/exceptions.py
hyblock_capital_sdk/models/__init__.py
hyblock_capital_sdk/models/anchored_binance_global_accounts.py
hyblock_capital_sdk/models/anchored_binance_top_trader_accounts.py
hyblock_capital_sdk/models/anchored_binance_top_trader_positions.py
hyblock_capital_sdk/models/anchored_binance_whale_retail_delta.py
hyblock_capital_sdk/models/anchored_cls.py
hyblock_capital_sdk/models/anchored_clsd.py
hyblock_capital_sdk/models/anchored_cvd.py
hyblock_capital_sdk/models/anchored_liq_levels_count.py
hyblock_capital_sdk/models/anchored_liq_levels_size.py
hyblock_capital_sdk/models/anchored_oi_delta.py
hyblock_capital_sdk/models/asks_increase_decrease.py
hyblock_capital_sdk/models/average_leverage_delta.py
hyblock_capital_sdk/models/average_leverage_used.py
hyblock_capital_sdk/models/bid_ask.py
hyblock_capital_sdk/models/bid_ask_delta.py
hyblock_capital_sdk/models/bid_ask_ratio.py
hyblock_capital_sdk/models/bid_ask_ratio_diff.py
hyblock_capital_sdk/models/bids_ask_spread.py
hyblock_capital_sdk/models/bids_increase_decrease.py
hyblock_capital_sdk/models/binance_global_accounts.py
hyblock_capital_sdk/models/binance_top_trader_accounts.py
hyblock_capital_sdk/models/binance_top_trader_positions.py
hyblock_capital_sdk/models/binance_true_retail_long_short.py
hyblock_capital_sdk-0.1.0.dist-info/LICENSE
hyblock_capital_sdk-0.1.0.dist-info/METADATA
hyblock_capital_sdk-0.1.0.dist-info/NOTICE
hyblock_capital_sdk-0.1.0.dist-info/WHEEL
hyblock_capital_sdk-0.1.0.dist-info/RECORD
