Metadata-Version: 2.3
Name: hyblock-capital-sdk
Version: 0.1.0
Summary: SDK no oficial para la API de Hyblock Capital - Cliente Python para trading de criptomonedas (Generado con OpenAPI Generator)
License: MIT
Keywords: trading,cryptocurrency,api,sdk,hyblock,capital,openapi
Author: Leonardo Jofre
Author-email: ljofre2146@gmail.com
Requires-Python: >=3.8.1,<4.0.0
Classifier: Development Status :: 4 - Beta
Classifier: Intended Audience :: Developers
Classifier: Intended Audience :: Financial and Insurance Industry
Classifier: License :: OSI Approved :: MIT License
Classifier: Operating System :: OS Independent
Classifier: Programming Language :: Python :: 3
Classifier: Programming Language :: Python :: 3.9
Classifier: Programming Language :: Python :: 3.10
Classifier: Programming Language :: Python :: 3.11
Classifier: Programming Language :: Python :: 3.12
Classifier: Programming Language :: Python :: 3.13
Classifier: Programming Language :: Python :: 3.8
Classifier: Topic :: Office/Business :: Financial :: Investment
Classifier: Topic :: Software Development :: Libraries :: Python Modules
Requires-Dist: pydantic (>=2.5.0,<3.0.0)
Requires-Dist: python-dateutil (>=2.8.2,<3.0.0)
Requires-Dist: typing-extensions (>=4.8.0,<5.0.0)
Requires-Dist: urllib3 (>=2.0.7,<3.0.0)
Project-URL: Documentation, https://docs.hyblock.capital/sdk
Project-URL: Homepage, https://github.com/ljofreflor/hyblock-capital-sdk
Project-URL: Repository, https://github.com/ljofreflor/hyblock-capital-sdk
